tecton_client/__about__.py
tecton_client/__init__.py
tecton_client/client_options.py
tecton_client/data_types.py
tecton_client/exceptions.py
tecton_client/http_client.py
tecton_client/requests.py
tecton_client/responses.py
tecton_client/tecton_client.py
tecton_client/utils.py
tecton_http_client_python-0.1.0b0.dist-info/METADATA
tecton_http_client_python-0.1.0b0.dist-info/WHEEL
tecton_http_client_python-0.1.0b0.dist-info/licenses/LICENSE.md
tecton_http_client_python-0.1.0b0.dist-info/RECORD
