Metadata-Version: 2.1
Name: tecton-http-client-python
Version: 0.1.0b0
Summary: A Python Client for the Tecton Online Inference
Project-URL: Source, https://github.com/tecton-ai/tecton-http-client-python
Project-URL: Documentation, https://tecton-ai.github.io/tecton-http-client-python/html/index.html
License-Expression: Apache-2.0
License-File: LICENSE.md
Requires-Python: >=3.8
Requires-Dist: aiohttp~=3.8.4
Requires-Dist: aioresponses~=0.7.4
Requires-Dist: pytest~=7.3.1
